cruncher/__init__.py
cruncher/core.py
cruncher/cruncher.py
cruncher/utils.py
cruncher-0.5.0.dist-info/LICENSE
cruncher-0.5.0.dist-info/METADATA
cruncher-0.5.0.dist-info/WHEEL
cruncher-0.5.0.dist-info/entry_points.txt
cruncher-0.5.0.dist-info/top_level.txt
cruncher-0.5.0.dist-info/RECORD
