Metadata-Version: 2.1
Name: cruncher
Version: 0.5.0
Summary: Simple CLI to optimize images for the web.
Home-page: https://github.com/danielmorell/cruncher
Author: Daniel Morell
Author-email: office@carintek.com
License: GPLv3+
Project-URL: Source Code, https://github.com/danielmorell/cruncher
Project-URL: Issue tracker, https://github.com/danielmorell/cruncher/issues
Classifier: Development Status :: 3 - Alpha
Classifier: Intended Audience :: Developers
Classifier: License :: OSI Approved :: GNU General Public License v3 or later (GPLv3+)
Classifier: Operating System :: OS Independent
Classifier: Programming Language :: Python
Classifier: Programming Language :: Python :: 3
Classifier: Programming Language :: Python :: 3.8
Classifier: Programming Language :: Python :: 3.9
Classifier: Programming Language :: Python :: 3.10
Requires-Python: >=3.8
License-File: LICENSE
Requires-Dist: click (==8.1.*)
Requires-Dist: pillow (==9.2.*)
